aws_sqs_batchlib/__init__.py
aws_sqs_batchlib/aws_sqs_batchlib.py
aws_sqs_batchlib/py.typed
aws_sqs_batchlib-3.1.0.dist-info/WHEEL
aws_sqs_batchlib-3.1.0.dist-info/METADATA
aws_sqs_batchlib-3.1.0.dist-info/RECORD
