Metadata-Version: 2.4
Name: aws-sqs-batchlib
Version: 3.1.0
Summary: Library for working with Amazon SQS
Author: Sami Jaktholm
Author-email: Sami Jaktholm <sjakthol@outlook.com>
License-Expression: MIT
Requires-Dist: boto3<2
Requires-Python: >=3.10
